protypo/__cli__.py
protypo/__init__.py
protypo/_version.py
protypo/conf/__init__.py
protypo/conf/about/__init__.yaml
protypo/conf/batch/__init__.yaml
protypo/conf/config.yaml
protypo/conf/dotenv/__init__.yaml
protypo/conf/hconf.yaml
protypo/conf/hydra/help/help.yaml
protypo/conf/hydra/job_logging/custom.yaml
protypo/conf/joblib/__init__.yaml
protypo/conf/mode/__init__.yaml
protypo/conf/mode/debug.yaml
protypo/conf/path/__batch__.yaml
protypo/conf/path/__default__.yaml
protypo/conf/path/__init__.yaml
protypo/conf/project/__init__.yaml
protypo/conf/task/__init__.yaml
protypo/project.toml
protypo/py.typed
protypo-0.1.2.dist-info/LICENSE
protypo-0.1.2.dist-info/METADATA
protypo-0.1.2.dist-info/WHEEL
protypo-0.1.2.dist-info/entry_points.txt
protypo-0.1.2.dist-info/RECORD
