Metadata-Version: 2.1
Name: protypo
Version: 0.1.2
Summary: A Python Library for Language Models
Home-page: https://protypo.entelecheia.ai
License: MIT
Author: Young Joon Lee
Author-email: entelecheia@hotmail.com
Requires-Python: >=3.8.1,<3.12
Classifier: License :: OSI Approved :: MIT License
Classifier: Programming Language :: Python :: 3
Classifier: Programming Language :: Python :: 3.9
Classifier: Programming Language :: Python :: 3.10
Classifier: Programming Language :: Python :: 3.11
Requires-Dist: hyfi (>=0.2.6,<0.3.0)
Requires-Dist: toml (>=0.10.2,<0.11.0)
